how_to_use_poetryy3/__init__.py
how_to_use_poetryy3-0.1.7.1.dist-info/WHEEL
how_to_use_poetryy3-0.1.7.1.dist-info/METADATA
how_to_use_poetryy3-0.1.7.1.dist-info/RECORD
