Metadata-Version: 2.1
Name: how-to-use-poetryy3
Version: 0.1.7.1
Summary: 
Author: ramazangur
Author-email: ramazangur@zoho.com
Requires-Python: >=3.10,<4.0
Classifier: Programming Language :: Python :: 3
Classifier: Programming Language :: Python :: 3.10
Requires-Dist: black (>=22.1.0,<23.0.0)
Requires-Dist: requests (>=2.27.1,<3.0.0)
